{"nodes": [{"id": "kaggle_mabe_mouse_behavior", "label": "MABe \u2014 Social Action Recognition in Mice", "file_type": "document", "source_file": "wiki/kaggle/mabe-mouse-behavior.md", "source_location": null, "source_url": null, "captured_at": null, "author": "Cameron Warren", "contributor": null}, {"id": "technique_temporal_classification", "label": "Temporal Classification (Pose/Keypoint Sequences)", "file_type": "document", "source_file": "wiki/kaggle/mabe-mouse-behavior.md", "source_location": null, "source_url": null, "captured_at": null, "author": null, "contributor": null}], "edges": [{"source": "kaggle_mabe_mouse_behavior", "target": "source_cameron_kaggle_profile", "relation": "references", "confidence": "EXTRACTED", "confidence_score": 1.0, "source_file": "wiki/kaggle/mabe-mouse-behavior.md", "source_location": "frontmatter sources", "weight": 1.0}, {"source": "kaggle_mabe_mouse_behavior", "target": "technique_temporal_classification", "relation": "references", "confidence": "EXTRACTED", "confidence_score": 1.0, "source_file": "wiki/kaggle/mabe-mouse-behavior.md", "source_location": "Domain context \u2014 temporal CNN/transformer over keypoint sequences", "weight": 1.0}, {"source": "kaggle_mabe_mouse_behavior", "target": "concept_computer_vision_kaggle", "relation": "conceptually_related_to", "confidence": "INFERRED", "confidence_score": 0.85, "source_file": "wiki/kaggle/mabe-mouse-behavior.md", "source_location": "tags: computer-vision, video", "weight": 0.85}, {"source": "kaggle_mabe_mouse_behavior", "target": "kaggle_jaguar_reidentification", "relation": "semantically_similar_to", "confidence": "INFERRED", "confidence_score": 0.68, "source_file": "wiki/kaggle/mabe-mouse-behavior.md", "source_location": "Both involve animal behavior / wildlife CV with non-standard domains; contrastive pretraining mentioned in both", "weight": 0.68}], "hyperedges": []}